ttp/__init__.py
ttp/formatters/__init__.py
ttp/formatters/csv_formatter.py
ttp/formatters/excel_formatter.py
ttp/formatters/jinja2_formatter.py
ttp/formatters/json_formatter.py
ttp/formatters/n2g_formatter.py
ttp/formatters/pprint_formatter.py
ttp/formatters/raw_formatter.py
ttp/formatters/table_formatter.py
ttp/formatters/tabulate_formatter.py
ttp/formatters/yaml_formatter.py
ttp/group/__init__.py
ttp/group/contains.py
ttp/group/contains_val.py
ttp/group/containsall.py
ttp/group/delete.py
ttp/group/equal.py
ttp/group/exclude.py
ttp/group/exclude_val.py
ttp/group/excludeall.py
ttp/group/expand.py
ttp/group/itemize.py
ttp/group/items2dict.py
ttp/group/lookup.py
ttp/group/macro.py
ttp/group/record.py
ttp/group/set_.py
ttp/group/sformat.py
ttp/group/to_converters.py
ttp/group/to_ip.py
ttp/group/validate_cerberus.py
ttp/group/void.py
ttp/input/__init__.py
ttp/input/commands.py
ttp/input/macro.py
ttp/input/test.py
ttp/lookup/__init__.py
ttp/lookup/geoip2.py
ttp/match/__init__.py
ttp/match/copy_.py
ttp/match/count.py
ttp/match/dns_lookups.py
ttp/match/geoip_lookup.py
ttp/match/ip.py
ttp/match/item.py
ttp/match/joinmatches.py
ttp/match/let.py
ttp/match/lookup.py
ttp/match/mac_eui.py
ttp/match/macro.py
ttp/match/raise_.py
ttp/match/re_.py
ttp/match/record.py
ttp/match/set_.py
ttp/match/string.py
ttp/match/to.py
ttp/match/unrange.py
ttp/match/uptimeparse.py
ttp/match/void.py
ttp/output/__init__.py
ttp/output/deepdiffer.py
ttp/output/is_equal.py
ttp/output/macro.py
ttp/output/transform.py
ttp/output/validate_cerberus.py
ttp/output/validate_yangson.py
ttp/patterns/__init__.py
ttp/patterns/get_pattern.py
ttp/returners/__init__.py
ttp/returners/file_returner.py
ttp/returners/self_returner.py
ttp/returners/syslog_returner.py
ttp/returners/terminal_returner.py
ttp/ttp.py
ttp/utils/__init__.py
ttp/utils/get_attributes.py
ttp/utils/guess.py
ttp/utils/load_python_exec_py2.py
ttp/utils/load_python_exec_py3.py
ttp/utils/loaders.py
ttp/utils/quick_parse.py
ttp/variable/__init__.py
ttp-0.9.3.dist-info/entry_points.txt
ttp-0.9.3.dist-info/LICENSE
ttp-0.9.3.dist-info/METADATA
ttp-0.9.3.dist-info/WHEEL
ttp-0.9.3.dist-info/RECORD
