Metadata-Version: 2.1
Name: ttp
Version: 0.9.3
Summary: Template Text Parser
Home-page: https://github.com/dmulyalin/ttp
License: MIT
Keywords: Parsing,TTP,regex
Author: Denis Mulyalin
Author-email: d.mulyalin@gmail.com
Maintainer: Denis Mulyalin
Maintainer-email: d.mulyalin@gmail.com
Requires-Python: >=2.7,<4.0
Classifier: License :: OSI Approved :: MIT License
Classifier: Operating System :: POSIX :: Linux
Classifier: Programming Language :: Python :: 2
Classifier: Programming Language :: Python :: 2.7
Classifier: Programming Language :: Python :: 3
Classifier: Programming Language :: Python :: 3.4
Classifier: Programming Language :: Python :: 3.5
Classifier: Programming Language :: Python :: 3.6
Classifier: Programming Language :: Python :: 3.7
Classifier: Programming Language :: Python :: 3.8
Classifier: Programming Language :: Python :: 3.9
Classifier: Programming Language :: Python :: 3.10
Classifier: Programming Language :: Python :: 3.11
Classifier: Programming Language :: Python :: 2.7
Classifier: Programming Language :: Python :: 3.10
Classifier: Programming Language :: Python :: 3.6
Classifier: Programming Language :: Python :: 3.7
Classifier: Programming Language :: Python :: 3.8
Classifier: Programming Language :: Python :: 3.9
Classifier: Topic :: Utilities
Provides-Extra: docs
Provides-Extra: full
Requires-Dist: Sphinx (==4.3.0) ; (python_version >= "3.7") and (extra == "docs")
Requires-Dist: cerberus (>=1.3.0,<1.4.0) ; (python_version >= "3.7") and (extra == "full")
Requires-Dist: deepdiff (>=5.8.0,<5.9.0) ; (python_version >= "3.7") and (extra == "full")
Requires-Dist: jinja2 (>=3.0.0,<3.1.0) ; (python_version >= "3.7") and (extra == "full")
Requires-Dist: n2g (>=0.2.0,<0.3.0) ; (python_version >= "3.7") and (extra == "full")
Requires-Dist: openpyxl (>=3.0.0,<3.1.0) ; (python_version >= "3.7") and (extra == "full")
Requires-Dist: pyyaml (==6.0) ; (python_version >= "3.7") and (extra == "full")
Requires-Dist: readthedocs-sphinx-search (==0.1.1) ; (python_version >= "3.7") and (extra == "docs")
Requires-Dist: sphinx_rtd_theme (==1.0.0) ; (python_version >= "3.7") and (extra == "docs")
Requires-Dist: sphinxcontrib-applehelp (==1.0.1) ; (python_version >= "3.7") and (extra == "docs")
Requires-Dist: sphinxcontrib-devhelp (==1.0.1) ; (python_version >= "3.7") and (extra == "docs")
Requires-Dist: sphinxcontrib-htmlhelp (==2.0.0) ; (python_version >= "3.7") and (extra == "docs")
Requires-Dist: sphinxcontrib-jsmath (==1.0.1) ; (python_version >= "3.7") and (extra == "docs")
Requires-Dist: sphinxcontrib-napoleon (==0.7) ; (python_version >= "3.7") and (extra == "docs")
Requires-Dist: sphinxcontrib-qthelp (==1.0.2) ; (python_version >= "3.7") and (extra == "docs")
Requires-Dist: sphinxcontrib-serializinghtml (==1.1.5) ; (python_version >= "3.7") and (extra == "docs")
Requires-Dist: sphinxcontrib-spelling (==7.2.1) ; (python_version >= "3.7") and (extra == "docs")
Requires-Dist: tabulate (>=0.8.0,<0.9.0) ; (python_version >= "3.7") and (extra == "full")
Requires-Dist: ttp_templates (<1.0.0) ; (python_version >= "3.7") and (extra == "full")
Requires-Dist: yangson (>=1.4.0,<1.5.0) ; (python_version >= "3.7") and (extra == "full")
Project-URL: Documentation, https://ttp.readthedocs.io/
Project-URL: Repository, https://github.com/dmulyalin/ttp
